pytng/__init__.py
pytng/pytng.c
pytng/pytng.cp314-win_amd64.pyd
pytng/pytng.pyx
pytng/include/compression/bwlzh.h
pytng/include/compression/bwt.h
pytng/include/compression/coder.h
pytng/include/compression/dict.h
pytng/include/compression/fixpoint.h
pytng/include/compression/huffman.h
pytng/include/compression/lz77.h
pytng/include/compression/merge_sort.h
pytng/include/compression/mtf.h
pytng/include/compression/my64bit.h
pytng/include/compression/rle.h
pytng/include/compression/tng_compress.h
pytng/include/compression/vals16.h
pytng/include/compression/warnmalloc.h
pytng/include/compression/widemuldiv.h
pytng/include/external/crc32.h
pytng/include/external/deflate.h
pytng/include/external/inffast.h
pytng/include/external/inffixed.h
pytng/include/external/inflate.h
pytng/include/external/inftrees.h
pytng/include/external/trees.h
pytng/include/external/zconf.h
pytng/include/external/zlib.h
pytng/include/external/zutil.h
pytng/include/tng/md5.h
pytng/include/tng/tng_io.h
pytng/include/tng/tng_io.hpp
pytng/include/tng/tng_io_fwd.h
pytng/include/tng/version.h
pytng/include/tng/version.h.in
pytng/src/compression/bwlzh.c
pytng/src/compression/bwt.c
pytng/src/compression/coder.c
pytng/src/compression/dict.c
pytng/src/compression/fixpoint.c
pytng/src/compression/huffman.c
pytng/src/compression/huffmem.c
pytng/src/compression/lz77.c
pytng/src/compression/merge_sort.c
pytng/src/compression/mtf.c
pytng/src/compression/rle.c
pytng/src/compression/tng_compress.c
pytng/src/compression/vals16.c
pytng/src/compression/warnmalloc.c
pytng/src/compression/widemuldiv.c
pytng/src/compression/xtc2.c
pytng/src/compression/xtc3.c
pytng/src/external/README
pytng/src/external/zlib/README
pytng/src/external/zlib/adler32.c
pytng/src/external/zlib/compress.c
pytng/src/external/zlib/crc32.c
pytng/src/external/zlib/deflate.c
pytng/src/external/zlib/inffast.c
pytng/src/external/zlib/inflate.c
pytng/src/external/zlib/inftrees.c
pytng/src/external/zlib/trees.c
pytng/src/external/zlib/uncompr.c
pytng-0.3.4.dist-info/licenses/LICENSE
pytng-0.3.4.dist-info/METADATA
pytng-0.3.4.dist-info/WHEEL
pytng-0.3.4.dist-info/top_level.txt
pytng-0.3.4.dist-info/RECORD
