Metadata-Version: 2.4
Name: pytng
Version: 0.3.4
Summary: Minimal Cython wrapper of the TNG trajectory library
Author: Max Linke, Richard J Gowers, Hugo MacDermott-Opeskin
Author-email: "Max Linke, Richard J Gowers, Hugo MacDermott-Opeskin" <max_linke@gmx.de>
Maintainer-email: MDAnalysis Core Developers <mdanalysis@numfocus.org>
Project-URL: Homepage, http://mdanalysis.org/pytng
Classifier: Development Status :: 6 - Mature
Classifier: Environment :: Console
Classifier: Intended Audience :: Science/Research
Classifier: License :: OSI Approved :: BSD License
Classifier: Operating System :: POSIX
Classifier: Operating System :: MacOS :: MacOS X
Classifier: Operating System :: Microsoft :: Windows
Classifier: Programming Language :: Python
Classifier: Programming Language :: Python :: 3.11
Classifier: Programming Language :: Python :: 3.12
Classifier: Programming Language :: Python :: 3.13
Classifier: Programming Language :: Python :: 3.14
Classifier: Programming Language :: C
Classifier: Topic :: Scientific/Engineering
Classifier: Topic :: Scientific/Engineering :: Bio-Informatics
Classifier: Topic :: Scientific/Engineering :: Chemistry
Classifier: Topic :: Software Development :: Libraries :: Python Modules
Requires-Python: >=3.9
License-File: LICENSE
Requires-Dist: numpy>1.22.3
Provides-Extra: test
Requires-Dist: pytest; extra == "test"
Requires-Dist: pytest-cov; extra == "test"
Provides-Extra: docs
Requires-Dist: mdanalysis-sphinx-theme; extra == "docs"
Requires-Dist: sphinx-sitemap; extra == "docs"
Dynamic: author
Dynamic: license-file
Dynamic: requires-python
